flask_reactjs/__init__.py
flask_reactjs/__main__.py
flask_reactjs/bundle.tar.gz
flask_react_simple-0.2.0.dist-info/LICENSE.txt
flask_react_simple-0.2.0.dist-info/METADATA
flask_react_simple-0.2.0.dist-info/WHEEL
flask_react_simple-0.2.0.dist-info/entry_points.txt
flask_react_simple-0.2.0.dist-info/top_level.txt
flask_react_simple-0.2.0.dist-info/RECORD
