Metadata-Version: 2.1
Name: flask-react-simple
Version: 0.2.0
Summary: UNKNOWN
Home-page: https://github.com/aweffr/flask-react-simple
Author: aweffr
Author-email: aweffr@foxmail.com
License: LICENSE.txt
Platform: UNKNOWN
Requires-Python: >=3.6.0
Requires-Dist: flask (>=1.0.2)
Requires-Dist: click (>=7.0)
